anomaly_detection_models.py
anomaly_detection_models-0.1.4.dist-info/LICENSE
anomaly_detection_models-0.1.4.dist-info/METADATA
anomaly_detection_models-0.1.4.dist-info/WHEEL
anomaly_detection_models-0.1.4.dist-info/top_level.txt
anomaly_detection_models-0.1.4.dist-info/RECORD
