Metadata-Version: 2.1
Name: anomaly-detection-models
Version: 0.1.4
Summary: Models for anomaly detection; see e.g. https://arxiv.org/abs/2009.02205
Home-page: https://github.com/luclepot/anomaly_detection_models
Author: Luc Le Pottier
Author-email: luclepot@umich.edu
License: UNKNOWN
Platform: UNKNOWN
Classifier: Programming Language :: Python :: 3
Classifier: License :: OSI Approved :: MIT License
Classifier: Operating System :: OS Independent
Requires-Python: >=3.6
Requires-Dist: matplotlib
Requires-Dist: numpy
Requires-Dist: scikit-learn (>=0.21.2)
Requires-Dist: pickleshare (>=0.7.5)
Requires-Dist: pandas (>=0.25.1)
